Mechalyze/__init__.py
Mechalyze/calc/__init__.py
Mechalyze/calc/fluids.py
Mechalyze/calc/mechanics.py
Mechalyze/calc/thermodynamics.py
Mechalyze/stats/__init__.py
Mechalyze/stats/history_analysis.py
Mechalyze/stats/prob.py
Mechalyze/stats/regression.py
Mechalyze/utils/__init__.py
Mechalyze/utils/constants.py
Mechalyze/utils/helpers.py
Mechalyze/viz/__init__.py
Mechalyze/viz/charts.py
Mechalyze/viz/plots.py
mechalyze-0.1.0a1.dist-info/licenses/LICENSE
mechalyze-0.1.0a1.dist-info/METADATA
mechalyze-0.1.0a1.dist-info/WHEEL
mechalyze-0.1.0a1.dist-info/top_level.txt
mechalyze-0.1.0a1.dist-info/RECORD
