Metadata-Version: 2.4
Name: Mechalyze
Version: 0.1.0a1
Summary: A mechanical engineering analysis package, which has tools for plotting values also uses stastical and historical analysis to give more precise answer.
Home-page: https://github.com/yourusername/mechalyse
Author: Mohnish S
Author-email: mohnishs2006@gmail.com
Classifier: Programming Language :: Python :: 3
Classifier: License :: OSI Approved :: MIT License
Classifier: Operating System :: OS Independent
Requires-Python: >=3.6
License-File: LICENSE
Requires-Dist: numpy
Requires-Dist: scipy
Requires-Dist: matplotlib
Dynamic: author
Dynamic: author-email
Dynamic: classifier
Dynamic: description
Dynamic: description-content-type
Dynamic: home-page
Dynamic: license-file
Dynamic: requires-dist
Dynamic: requires-python
Dynamic: summary
